[
  {
    "category": "PTS",
    "rank": 1,
    "code": "4075",
    "name": "4075",
    "news_list_url": "https://kabutan.jp/stock/news?code=4075",
    "materials": [
      {
        "title": "ブレインズ---ストップ高買い気配、ヒューマノイドロボットによる製造現場自働化の実証結果を発表",
        "url": "https://kabutan.jp/stock/news?code=4075&b=n202603060745",
        "date": ""
      },
      {
        "title": "ブレインズがＳ高カイ気配、製造現場のヒューマノイドロボット活用実証で一部工程自動化",
        "url": "https://kabutan.jp/stock/news?code=4075&b=n202603060376",
        "date": ""
      },
      {
        "title": "ネオジャパンが大幅続伸、全文検索システムの販売・提供で業務提携",
        "url": "https://kabutan.jp/stock/news?code=4075&b=n202602250598",
        "date": ""
      }
    ],
    "time": "2026-03-07 15:42"
  },
  {
    "category": "PTS",
    "rank": 2,
    "code": "4031",
    "name": "4031",
    "news_list_url": "https://kabutan.jp/stock/news?code=4031",
    "materials": [
      {
        "title": "片倉コープアグリ：農業ソリューション深化と化学品の海外展開で成長加速へ",
        "url": "https://kabutan.jp/stock/news?code=4031&b=n202512100744",
        "date": ""
      },
      {
        "title": "農政大転換で脚光、成長産業へ評価急上昇中の「農業関連」銘柄に刮目 ＜株探トップ特集＞",
        "url": "https://kabutan.jp/stock/news?code=4031&b=n202509101041",
        "date": ""
      }
    ],
    "time": "2026-03-07 15:42"
  },
  {
    "category": "PTS",
    "rank": 3,
    "code": "318A",
    "name": "318A",
    "news_list_url": "https://kabutan.jp/stock/news?code=318A",
    "materials": [],
    "time": "2026-03-07 15:42"
  },
  {
    "category": "PTS",
    "rank": 4,
    "code": "1671",
    "name": "1671",
    "news_list_url": "https://kabutan.jp/stock/news?code=1671",
    "materials": [
      {
        "title": "ＷＴＩ原油など石油ＥＴＦが高い、中東緊迫化でＷＴＩ価格は８０ドル台に急上昇",
        "url": "https://kabutan.jp/stock/news?code=1671&b=n202603060451",
        "date": ""
      },
      {
        "title": "野村原油など原油ＥＴＦが高い、中東情勢の緊迫化でＷＴＩは一時８カ月ぶり高値",
        "url": "https://kabutan.jp/stock/news?code=1671&b=n202603040346",
        "date": ""
      },
      {
        "title": "原油連動のＥＴＦ・ＥＴＮは軒並み高、米イスラエルがイラン攻撃でＷＴＩ急伸",
        "url": "https://kabutan.jp/stock/news?code=1671&b=n202603020258",
        "date": ""
      }
    ],
    "time": "2026-03-07 15:42"
  },
  {
    "category": "PTS",
    "rank": 5,
    "code": "1699",
    "name": "1699",
    "news_list_url": "https://kabutan.jp/stock/news?code=1699",
    "materials": [
      {
        "title": "野村原油など原油ＥＴＦが高い、中東情勢の緊迫化でＷＴＩは一時８カ月ぶり高値",
        "url": "https://kabutan.jp/stock/news?code=1699&b=n202603040346",
        "date": ""
      },
      {
        "title": "原油連動のＥＴＦ・ＥＴＮは軒並み高、米イスラエルがイラン攻撃でＷＴＩ急伸",
        "url": "https://kabutan.jp/stock/news?code=1699&b=n202603020258",
        "date": ""
      }
    ],
    "time": "2026-03-07 15:42"
  },
  {
    "category": "PTS",
    "rank": 6,
    "code": "1366",
    "name": "1366",
    "news_list_url": "https://kabutan.jp/stock/news?code=1366",
    "materials": [],
    "time": "2026-03-07 15:42"
  },
  {
    "category": "PTS",
    "rank": 7,
    "code": "3315",
    "name": "3315",
    "news_list_url": "https://kabutan.jp/stock/news?code=3315",
    "materials": [],
    "time": "2026-03-07 15:42"
  },
  {
    "category": "PTS",
    "rank": 8,
    "code": "5035",
    "name": "5035",
    "news_list_url": "https://kabutan.jp/stock/news?code=5035",
    "materials": [],
    "time": "2026-03-07 15:42"
  },
  {
    "category": "PTS",
    "rank": 9,
    "code": "1459",
    "name": "1459",
    "news_list_url": "https://kabutan.jp/stock/news?code=1459",
    "materials": [],
    "time": "2026-03-07 15:42"
  },
  {
    "category": "PTS",
    "rank": 10,
    "code": "1356",
    "name": "1356",
    "news_list_url": "https://kabutan.jp/stock/news?code=1356",
    "materials": [],
    "time": "2026-03-07 15:42"
  },
  {
    "category": "PTS",
    "rank": 11,
    "code": "9130",
    "name": "9130",
    "news_list_url": "https://kabutan.jp/stock/news?code=9130",
    "materials": [
      {
        "title": "明日の株式相場に向けて＝買い場到来か、ここでの選択肢と個別戦略",
        "url": "https://kabutan.jp/stock/news?code=9130&b=n202603031091",
        "date": ""
      },
      {
        "title": "共栄タは一時Ｓ高、ホルムズ海峡封鎖で思惑的な買いを集める",
        "url": "https://kabutan.jp/stock/news?code=9130&b=n202603030741",
        "date": ""
      },
      {
        "title": "共栄タについて、三井住友海上火災保険は保有割合が5％未満に減少したと報告 [変更報告書No.4]",
        "url": "https://kabutan.jp/stock/news?code=9130&b=n202602050965",
        "date": ""
      }
    ],
    "time": "2026-03-07 15:42"
  },
  {
    "category": "PTS",
    "rank": 12,
    "code": "1360",
    "name": "1360",
    "news_list_url": "https://kabutan.jp/stock/news?code=1360",
    "materials": [],
    "time": "2026-03-07 15:42"
  },
  {
    "category": "PTS",
    "rank": 13,
    "code": "1357",
    "name": "1357",
    "news_list_url": "https://kabutan.jp/stock/news?code=1357",
    "materials": [
      {
        "title": "【北浜流一郎のズバリ株先見！】 ─\"最強軍団\"が注目する「2026年勝負銘柄」！",
        "url": "https://kabutan.jp/stock/news?code=1357&b=n202601110009",
        "date": ""
      },
      {
        "title": "杉村富生が斬る！午年「有望株！」 ＜新春お年玉企画＞",
        "url": "https://kabutan.jp/stock/news?code=1357&b=n202601010077",
        "date": ""
      }
    ],
    "time": "2026-03-07 15:42"
  },
  {
    "category": "PTS",
    "rank": 14,
    "code": "6521",
    "name": "6521",
    "news_list_url": "https://kabutan.jp/stock/news?code=6521",
    "materials": [
      {
        "title": "ＱＤレーザなどレーザー関連株に投資マネー集中、レーザーは防衛関連のコアテクノロジー分野",
        "url": "https://kabutan.jp/stock/news?code=6521&b=n202603050440",
        "date": ""
      },
      {
        "title": "デジタル新時代の先端技術、輝き放つ「光電融合技術」関連をロックオン ＜株探トップ特集＞",
        "url": "https://kabutan.jp/stock/news?code=6521&b=n202603041208",
        "date": ""
      },
      {
        "title": "明日の株式相場に向けて＝買い場到来か、ここでの選択肢と個別戦略",
        "url": "https://kabutan.jp/stock/news?code=6521&b=n202603031091",
        "date": ""
      }
    ],
    "time": "2026-03-07 15:42"
  },
  {
    "category": "PTS",
    "rank": 15,
    "code": "6963",
    "name": "6963",
    "news_list_url": "https://kabutan.jp/stock/news?code=6963",
    "materials": [
      {
        "title": "ロームについて、野村証は保有割合が減少したと報告 [変更報告書No.11]",
        "url": "https://kabutan.jp/stock/news?code=6963&b=n202602180823",
        "date": ""
      },
      {
        "title": "個人投資家・有限亭玉介：【メモリ・半導体需要は継続】次世代パワー半導体開発は止まらない【FISCOソーシャルレポーター】",
        "url": "https://kabutan.jp/stock/news?code=6963&b=n202602070172",
        "date": ""
      }
    ],
    "time": "2026-03-07 15:42"
  },
  {
    "category": "S高",
    "rank": 1,
    "code": "157A",
    "name": "157A",
    "news_list_url": "https://kabutan.jp/stock/news?code=157A",
    "materials": [
      {
        "title": "グリーンモンスター---続落、投資スクール事業「Financial Free College」を譲受し新会社設立も",
        "url": "https://kabutan.jp/stock/news?code=157A&b=n202603020489",
        "date": ""
      }
    ],
    "time": "2026-03-07 15:42"
  },
  {
    "category": "S高",
    "rank": 2,
    "code": "3556",
    "name": "3556",
    "news_list_url": "https://kabutan.jp/stock/news?code=3556",
    "materials": [
      {
        "title": "リネットジャパン---ストップ高買い気配、障がい者グループホーム業界でロールアップ型M&Aの検討を開始",
        "url": "https://kabutan.jp/stock/news?code=3556&b=n202603060416",
        "date": ""
      },
      {
        "title": "リネットＪがカイ気配、障害者グループホーム関連のロールアップ型Ｍ＆Ａ着手",
        "url": "https://kabutan.jp/stock/news?code=3556&b=n202603060336",
        "date": ""
      }
    ],
    "time": "2026-03-07 15:42"
  },
  {
    "category": "S高",
    "rank": 3,
    "code": "4075",
    "name": "4075",
    "news_list_url": "https://kabutan.jp/stock/news?code=4075",
    "materials": [
      {
        "title": "ブレインズ---ストップ高買い気配、ヒューマノイドロボットによる製造現場自働化の実証結果を発表",
        "url": "https://kabutan.jp/stock/news?code=4075&b=n202603060745",
        "date": ""
      },
      {
        "title": "ブレインズがＳ高カイ気配、製造現場のヒューマノイドロボット活用実証で一部工程自動化",
        "url": "https://kabutan.jp/stock/news?code=4075&b=n202603060376",
        "date": ""
      },
      {
        "title": "ネオジャパンが大幅続伸、全文検索システムの販売・提供で業務提携",
        "url": "https://kabutan.jp/stock/news?code=4075&b=n202602250598",
        "date": ""
      }
    ],
    "time": "2026-03-07 15:42"
  },
  {
    "category": "S高",
    "rank": 4,
    "code": "6963",
    "name": "6963",
    "news_list_url": "https://kabutan.jp/stock/news?code=6963",
    "materials": [
      {
        "title": "ロームについて、野村証は保有割合が減少したと報告 [変更報告書No.11]",
        "url": "https://kabutan.jp/stock/news?code=6963&b=n202602180823",
        "date": ""
      },
      {
        "title": "個人投資家・有限亭玉介：【メモリ・半導体需要は継続】次世代パワー半導体開発は止まらない【FISCOソーシャルレポーター】",
        "url": "https://kabutan.jp/stock/news?code=6963&b=n202602070172",
        "date": ""
      }
    ],
    "time": "2026-03-07 15:42"
  },
  {
    "category": "S高",
    "rank": 5,
    "code": "7719",
    "name": "7719",
    "news_list_url": "https://kabutan.jp/stock/news?code=7719",
    "materials": [
      {
        "title": "東京衡機---ストップ高買い気配、対米投融資第2弾として原発など検討と伝わり",
        "url": "https://kabutan.jp/stock/news?code=7719&b=n202603050497",
        "date": ""
      },
      {
        "title": "東京衡機は反落、東証が監理銘柄（確認中）に指定",
        "url": "https://kabutan.jp/stock/news?code=7719&b=n202603020215",
        "date": ""
      }
    ],
    "time": "2026-03-07 15:42"
  }
]